cythonevparser/LICENSE
cythonevparser/README.MD
cythonevparser/__init__.py
cythonevparser/evparse.pyx
cythonevparser/evparse_compile.py
cythonevparser/requirements.txt
cythonevparser/thirdparty.json
cythonevparser-0.15.dist-info/LICENSE.rst
cythonevparser-0.15.dist-info/METADATA
cythonevparser-0.15.dist-info/WHEEL
cythonevparser-0.15.dist-info/top_level.txt
cythonevparser-0.15.dist-info/RECORD
