Metadata-Version: 2.1
Name: cythonevparser
Version: 0.15
Summary: eventparser parser for Android
Home-page: https://github.com/hansalemaos/cythonevparser
Author: Johannes Fischer
Author-email: aulasparticularesdealemaosp@gmail.com
License: MIT
Keywords: uiautomator,events
Classifier: Development Status :: 4 - Beta
Classifier: Programming Language :: Python :: 3 :: Only
Classifier: Programming Language :: Python :: 3.10
Classifier: Topic :: Software Development :: Libraries :: Python Modules
Classifier: Topic :: Utilities
License-File: LICENSE.rst
Requires-Dist: Cython
Requires-Dist: adbshellexecuter
Requires-Dist: cythoncubicspline
Requires-Dist: exceptdrucker
Requires-Dist: flatten-any-dict-iterable-or-whatsoever
Requires-Dist: nested2nested
Requires-Dist: numpy
Requires-Dist: pandas
Requires-Dist: parifinder
Requires-Dist: regex
Requires-Dist: setuptools
